django_modals/__init__.py
django_modals/apps.py
django_modals/datatables.py
django_modals/decorators.py
django_modals/fields.py
django_modals/form_helpers.py
django_modals/forms.py
django_modals/helper.py
django_modals/includes.py
django_modals/messages.py
django_modals/mixins.py
django_modals/modal_upload.py
django_modals/modals.py
django_modals/processes.py
django_modals/task_modals.py
django_modals/url_helper.py
django_modals/model_fields/__init__.py
django_modals/model_fields/colour.py
django_modals/static/django_modals/css/bootstrap4-toggle.min.css
django_modals/static/django_modals/css/modals.css
django_modals/static/django_modals/css/select2.min.css
django_modals/static/django_modals/jquery-month-picker/css/MonthPicker.min.css
django_modals/static/django_modals/jquery-month-picker/js/MonthPicker.min.js
django_modals/static/django_modals/jquery_ui_limited/css/jquery-ui.min.css
django_modals/static/django_modals/jquery_ui_limited/css/images/ui-icons_444444_256x240.png
django_modals/static/django_modals/jquery_ui_limited/css/images/ui-icons_555555_256x240.png
django_modals/static/django_modals/jquery_ui_limited/css/images/ui-icons_777620_256x240.png
django_modals/static/django_modals/jquery_ui_limited/css/images/ui-icons_777777_256x240.png
django_modals/static/django_modals/jquery_ui_limited/css/images/ui-icons_cc0000_256x240.png
django_modals/static/django_modals/jquery_ui_limited/css/images/ui-icons_ffffff_256x240.png
django_modals/static/django_modals/jquery_ui_limited/js/jquery-ui.min.js
django_modals/static/django_modals/js/bootstrap4-toggle.min.js
django_modals/static/django_modals/js/bootstrap4-toggle.min.js.map
django_modals/static/django_modals/js/jquery.formset.js
django_modals/static/django_modals/js/modals.js
django_modals/static/django_modals/js/modals.min.js
django_modals/static/django_modals/js/modals_legacy.js
django_modals/static/django_modals/js/select2.min.js
django_modals/static/django_modals/js/widget_select2.js
django_nested_modals-0.0.24.dist-info/LICENSE
django_nested_modals-0.0.24.dist-info/METADATA
django_nested_modals-0.0.24.dist-info/WHEEL
django_nested_modals-0.0.24.dist-info/top_level.txt
django_nested_modals-0.0.24.dist-info/RECORD
