Metadata-Version: 2.1
Name: django-nested-modals
Version: 0.0.24
Summary: Django app to implement Bootstrap nested modals
Home-page: https://github.com/jonesim/django-modals
Author: Ian Jones
Classifier: Programming Language :: Python :: 3
Classifier: License :: OSI Approved :: MIT License
Classifier: Operating System :: OS Independent
Requires-Python: >=3.6
License-File: LICENSE
Requires-Dist: django-ajax-helpers >=0.0.22
Requires-Dist: django-crispy-forms
